daskperiment/__init__.py
daskperiment/command.py
daskperiment/config.py
daskperiment/testing.py
daskperiment/version.py
daskperiment/backend/__init__.py
daskperiment/backend/base.py
daskperiment/backend/local.py
daskperiment/backend/mongo.py
daskperiment/backend/redis.py
daskperiment/board/__init__.py
daskperiment/board/board.py
daskperiment/board/component.py
daskperiment/board/utils.py
daskperiment/board/statics/css/styles.css
daskperiment/board/templates/index.html
daskperiment/core/__init__.py
daskperiment/core/analyze.py
daskperiment/core/code.py
daskperiment/core/errors.py
daskperiment/core/experiment.py
daskperiment/core/parameter.py
daskperiment/core/parser.py
daskperiment/core/trial.py
daskperiment/core/metric/__init__.py
daskperiment/core/metric/base.py
daskperiment/core/metric/local.py
daskperiment/core/metric/nosql.py
daskperiment/core/metric/redis.py
daskperiment/core/trial/__init__.py
daskperiment/core/trial/base.py
daskperiment/core/trial/local.py
daskperiment/core/trial/nosql.py
daskperiment/environment/__init__.py
daskperiment/environment/base.py
daskperiment/environment/environment.py
daskperiment/environment/git.py
daskperiment/environment/platform.py
daskperiment/environment/python.py
daskperiment/io/__init__.py
daskperiment/io/json.py
daskperiment/io/pickle.py
daskperiment/tests/__init__.py
daskperiment/tests/test_command.py
daskperiment/tests/backend/__init__.py
daskperiment/tests/backend/test_backend.py
daskperiment/tests/backend/test_nosql.py
daskperiment/tests/board/__init__.py
daskperiment/tests/board/test_board.py
daskperiment/tests/board/test_component.py
daskperiment/tests/board/test_utils.py
daskperiment/tests/core/__init__.py
daskperiment/tests/core/test_code.py
daskperiment/tests/core/test_parameter.py
daskperiment/tests/core/test_parser.py
daskperiment/tests/core/experiment/__init__.py
daskperiment/tests/core/experiment/base.py
daskperiment/tests/core/experiment/test_local.py
daskperiment-0.5.0.dist-info/DESCRIPTION.rst
daskperiment-0.5.0.dist-info/METADATA
daskperiment-0.5.0.dist-info/RECORD
daskperiment-0.5.0.dist-info/WHEEL
daskperiment-0.5.0.dist-info/entry_points.txt
daskperiment-0.5.0.dist-info/metadata.json
daskperiment-0.5.0.dist-info/top_level.txt
