Metadata-Version: 2.0
Name: daskperiment
Version: 0.5.0
Summary: A lightweight tool to perform reproducible machine learning experiment using Dask.
Home-page: http://daskperiment.readthedocs.org/en/stable
Author: sinhrks
Author-email: sinhrks@gmail.com
License: BSD
Platform: UNKNOWN
Requires-Dist: pandas (>=0.19.0)
Requires-Dist: dask (>=1.0.0)
Requires-Dist: click (>=7.0.0)
Requires-Dist: cloudpickle (>=0.7.0)
Requires-Dist: pyparsing (>=2.3.0)
Requires-Dist: py-cpuinfo (>=4.0.0)
Requires-Dist: gitpython (>=2.0.0)
Requires-Dist: setuptools (>=40.0.0)
Requires-Dist: flask (>=1.0.0)
